strconstruct/__init__.py
strconstruct/construct_base.py
strconstruct/str_check.py
strconstruct/str_const.py
strconstruct/str_construct_exceptions.py
strconstruct/str_default.py
strconstruct/str_float.py
strconstruct/str_if.py
strconstruct/str_if_then_else.py
strconstruct/str_int.py
strconstruct/str_rebuild.py
strconstruct/str_stop_if.py
strconstruct/str_struct.py
strconstruct/str_switch.py
strconstruct-0.0.1.dist-info/LICENSE
strconstruct-0.0.1.dist-info/METADATA
strconstruct-0.0.1.dist-info/WHEEL
strconstruct-0.0.1.dist-info/top_level.txt
strconstruct-0.0.1.dist-info/RECORD
