Metadata-Version: 2.1
Name: strconstruct
Version: 0.0.1
Summary: A declarative parser and builder for string-based protocols
License: BSD 3-Clause License
Project-URL: Homepage, https://github.com/ValaJeyhani/strContruct
Project-URL: Documentation, https://strconstruct.readthedocs.io/en/latest/
Project-URL: Repository, https://github.com/ValaJeyhani/strContruct
Keywords: protocol,declarative,parse,build,string
Requires-Python: >=3.6
License-File: LICENSE
